MIPS32_Pipelined.srcs/sources_1/new/top.v
`timescale 1ns / 1ps

// with pipeline, need to maintain and check two extra flags at each phase, HALT , TAKEN_BRANCH

module pipe_MIPS32(clk1, clk2);
    input clk1, clk2;
    reg[31:0] PC, IF_ID_IR,IF_ID_NPC;
    reg[31:0] ID_EX_IR, ID_EX_NPC, ID_EX_A, ID_EX_B,ID_EX_Imm;
    reg[2:0]  ID_EX_type, EX_MEM_type, MEM_WB_type;
    reg[31:0] EX_MEM_IR, EX_MEM_ALUOut,EX_MEM_B;
    reg EX_MEM_cond;
    reg[31:0] MEM_WB_IR, MEM_WB_ALUOut, MEM_WB_LMD;
    reg[31:0] Reg[0:31];
    reg[31:0] Mem[0:1023];  
    
    parameter ADD=6'b000000, SUB=6'b000001, AND=6'b000010, OR=6'b000011,
              SLT=6'b000100, MUL=6'b000101, HLT=6'b111111, LW=6'b001000,
              SW=6'b001001, ADDI=6'b001010, SUBI=6'b000010, SLTI=6'b001100,
              BNEQZ=6'b001101, BEQZ=6'b001110;
    
    parameter RR_ALU=3'b000, RM_ALU=3'b001, LOAD=3'b010, STORE=3'b011, BRANCH= 3'b100, HALT=3'b101;
    reg HALTED; // set after halt instruction is completed(In WB stage) , single bit flag flip flop
    //know at decode phase
    reg TAKEN_BRANCH; // reguired to disable instructions after branch, single bit flag flip flop
    // known after EX phase
    
    
    // IF - read insruction , store in IR
    always @(posedge clk1)
        if(HALTED ==0) // If halted==1 , no need to fetch further any insruction
        begin
          if((EX_MEM_IR[31:26]== BEQZ) && (EX_MEM_cond == 1) || // cond = (A==0), cond ==1
             (EX_MEM_IR[31:26]== BNEQZ) &&  (EX_MEM_cond == 0)) // cond = (A==1), cond ==0
             // both cases needs to jump, Instruction register will not fetch from normal PC, rather from
              //Mem[EX_MEM_ALUOut]
              begin
                IF_ID_IR <= #2 Mem[EX_MEM_ALUOut];
                TAKEN_BRANCH<= #2 1'b1; // indicae, branchis actually taken
                IF_ID_NPC <= #2 EX_MEM_ALUOut +1;
                PC <= #2 EX_MEM_ALUOut +1;
              end
           else // if no branch take, proceed normal normal execution
           begin
             IF_ID_IR <= #2 Mem[PC];
             IF_ID_NPC <= #2 PC+1;
             PC <= #2 PC+1;
           end
         end
         
         
     // ID - decode:- decode insruction type, prefetch 2 sourse registers, sign exteded 16 bit off bit
     //opcode [31:26], rs[25:21], rt[20:16], rd[15:11], 
     
    always @(posedge clk2)
        if(HALTED ==0)
        begin
            if(IF_ID_IR[25:21]== 5'b00000) ID_EX_A <= 0;
            else ID_EX_A <= #2 Reg[IF_ID_IR[25:21]]; // rs
            
            if(IF_ID_IR[20:16]== 5'b00000) ID_EX_B <= 0;
            else ID_EX_B <= #2 Reg[IF_ID_IR[20:16]]; // rt
            
            ID_EX_NPC <= #2 IF_ID_NPC;
            ID_EX_IR <= #2 IF_ID_IR;
            ID_EX_Imm <= #2  {{16{IF_ID_IR[15]}} , {IF_ID_IR[15:0]}};
            
            //check opcode again, depending on opcode , assign value to type
            
            case(IF_ID_IR[31:26])
              ADD, SUB, AND, OR, SLT, MUL: ID_EX_type <= #2 RR_ALU;
              ADDI, SUBI, SLTI:            ID_EX_type <= #2 RM_ALU;
              LW:                          ID_EX_type <= #2 LOAD;
              SW:                          ID_EX_type <= #2 STORE;
              BNEQZ, BEQZ:                 ID_EX_type <= #2 BRANCH;
              HLT:                         ID_EX_type <= #2 HALT;
              default:                     ID_EX_type <= #2 HALT;
            endcase
          end
          
    // Ex stage
    always @(posedge clk1)
    if(HALTED==0)
    begin
      EX_MEM_type <= #2 ID_EX_type;
      EX_MEM_IR <= #2 ID_EX_IR;
      TAKEN_BRANCH <= #2 0;
      case(ID_EX_type)
          RR_ALU: begin
                  case(ID_EX_IR[31:26]) // Opcode
                    ADD:         EX_MEM_ALUOut <= #2 ID_EX_A + ID_EX_B;
                    SUB:         EX_MEM_ALUOut <= #2 ID_EX_A - ID_EX_B;
                    AND:         EX_MEM_ALUOut <= #2 ID_EX_A & ID_EX_B;
                    OR:          EX_MEM_ALUOut <= #2 ID_EX_A | ID_EX_B;
                    SLT:         EX_MEM_ALUOut <= #2 ID_EX_A < ID_EX_B;
                    MUL:         EX_MEM_ALUOut <= #2 ID_EX_A * ID_EX_B;
                    default:     EX_MEM_ALUOut <= #2 32'hxxxxxxxx;
                  endcase
                 end
                 
          RM_ALU: begin
                  case(ID_EX_IR[31:26]) // Opcode
                    ADDI:         EX_MEM_ALUOut <= #2 ID_EX_A + ID_EX_Imm;
                    SUBI:         EX_MEM_ALUOut <= #2 ID_EX_A - ID_EX_Imm;
                    SLTI:         EX_MEM_ALUOut <= #2 ID_EX_A < ID_EX_Imm;
                    default:      EX_MEM_ALUOut <= #2 32'hxxxxxxxx;
                  endcase
                 end
                 
          LOAD, STORE:     // calculating address of memory 
                    begin
                       EX_MEM_ALUOut <= #2 ID_EX_A + ID_EX_Imm;
                       EX_MEM_B <= #2 ID_EX_B; 
                    end
                              
          BRANCH:     // calculating address of memory  // also going feedback to IF stage
                    begin
                       EX_MEM_ALUOut <= #2 ID_EX_NPC + ID_EX_Imm;
                       EX_MEM_cond <= #2 (ID_EX_A ==0); 
                    end
      endcase
    end
    
    // MEM stage
    always @(posedge clk2)
      if(HALTED ==0)
      begin
        MEM_WB_type <= #2 EX_MEM_type;
        MEM_WB_IR <= #2 EX_MEM_IR;
        
        case(EX_MEM_type)
          RR_ALU, RM_ALU: 
                    MEM_WB_ALUOut <= #2 EX_MEM_ALUOut;
          LOAD:     MEM_WB_LMD <= #2 Mem[EX_MEM_ALUOut];
          STORE:    if(TAKEN_BRANCH==0)
                       Mem[EX_MEM_ALUOut] <= #2 EX_MEM_B;
        endcase
      end
      
      // WB stage
    always @(posedge clk1)
        begin
          if(TAKEN_BRANCH ==0)
          case(MEM_WB_type)
            RR_ALU :   Reg[MEM_WB_IR[15:11]] <= #2 MEM_WB_ALUOut; //rd
            RM_ALU :   Reg[MEM_WB_IR[20:16]] <= #2 MEM_WB_ALUOut; //rt
            LOAD :     Reg[MEM_WB_IR[20:16]] <= #2 MEM_WB_LMD; //rt
            HALT :     HALTED <= #2 1'b1;
          endcase
        end
endmodule;

MIPS32_Pipelined.srcs/sim_1/new/test_mips32.v
`timescale 1ns / 1ps

module test_mips32;
  reg clk1, clk2;
  integer k;
  pipe_MIPS32 mips(clk1, clk2);
  initial
    begin
      clk1=0; clk2=0;
      repeat (20)
      begin
        #5 clk1 =1; #5 clk1 =0; //generating two phase clock
        #5 clk2 =1; #5 clk2 =0;
      end   
    end
    
    // instruction load (instruction + dummy instructions)
  initial
    begin
      for(k=0; k<31; k =k+1)
        mips.Reg[k] = k;
        
      mips.Mem[0] = 32'h2801000a;       // ADDI  R1, R0, 10
      mips.Mem[1] = 32'h28020014;       // ADDI  R2, R0, 20
      mips.Mem[2] = 32'h28030019;       // ADDI  R3, R0, 25
      mips.Mem[3] = 32'h0ce77800;       // OR  R7, R7, R7 // dummy instriction
      mips.Mem[4] = 32'h0ce77800;       // OR  R7, R7, R7 // dummy instriction
      mips.Mem[5] = 32'h00222000;       // ADD  R4, R1, R2
      mips.Mem[6] = 32'h0ce77800;       // OR  R7, R7, R7 // dummy instriction 
      mips.Mem[7] = 32'h00832800;       // ADD  R4, R1, R2
      mips.Mem[8] = 32'hfc000000;       // HLT
     
      mips.HALTED = 0;
      mips.PC= 0;
      mips.TAKEN_BRANCH =0;
      
      #280
      for (k=0; k < 6; k = k+1)
        $display("R%1d - %2d", k, mips.Reg[k]);
    end
    
    initial
      begin
        $dumpfile("mips.vcd");
        $dumpvars(0, test_mips32);
        #300 $finish;
      end

endmodule

MIPS32_Pipelined.sim/sim_1/behav/xsim/mips.vcd
$date
   Mon Mar  6 16:32:03 2023
$end
$version
  2022.2
$end
$timescale
  1ps
$end
$scope module test_mips32 $end
$var reg 1 ! clk1 $end
$var reg 1 " clk2 $end
$var integer 32 # k [31:0] $end
$scope module mips $end
$var wire 1 $ clk1 $end
$var wire 1 % clk2 $end
$var reg 32 & PC [31:0] $end
$var reg 32 ' IF_ID_IR [31:0] $end
$var reg 32 ( IF_ID_NPC [31:0] $end
$var reg 32 ) ID_EX_IR [31:0] $end
$var reg 32 * ID_EX_NPC [31:0] $end
$var reg 32 + ID_EX_A [31:0] $end
$var reg 32 , ID_EX_B [31:0] $end
$var reg 32 - ID_EX_Imm [31:0] $end
$var reg 3 . ID_EX_type [2:0] $end
$var reg 3 / EX_MEM_type [2:0] $end
$var reg 3 0 MEM_WB_type [2:0] $end
$var reg 32 1 EX_MEM_IR [31:0] $end
$var reg 32 2 EX_MEM_ALUOut [31:0] $end
$var reg 32 3 EX_MEM_B [31:0] $end
$var reg 1 4 EX_MEM_cond $end
$var reg 32 5 MEM_WB_IR [31:0] $end
$var reg 32 6 MEM_WB_ALUOut [31:0] $end
$var reg 32 7 MEM_WB_LMD [31:0] $end
$var reg 1 8 HALTED $end
$var reg 1 9 TAKEN_BRANCH $end
$upscope $end
$upscope $end
$enddefinitions $end
#0
$dumpvars
0!
0"
b11111 #
0$
0%
b0 &
bx '
bx (
bx )
bx *
bx +
bx ,
bx -
bx .
bx /
bx 0
bx 1
bx 2
bx 3
x4
bx 5
bx 6
bx 7
08
09
$end
#5000
1!
1$
#7000
b1 &
b101000000000010000000000001010 '
b1 (
#10000
0!
0$
#15000
1"
1%
b0 +
#17000
b101000000000010000000000001010 )
b1 *
b1 ,
b1010 -
b1 .
#20000
0"
0%
#25000
1!
1$
#27000
b10 &
b101000000000100000000000010100 '
b10 (
b1 /
b101000000000010000000000001010 1
b1010 2
#30000
0!
0$
#35000
1"
1%
#37000
b101000000000100000000000010100 )
b10 *
b10 ,
b10100 -
b1 0
b101000000000010000000000001010 5
b1010 6
#40000
0"
0%
#45000
1!
1$
#47000
b11 &
b101000000000110000000000011001 '
b11 (
b101000000000100000000000010100 1
b10100 2
#50000
0!
0$
#55000
1"
1%
#57000
b101000000000110000000000011001 )
b11 *
b11 ,
b11001 -
b101000000000100000000000010100 5
b10100 6
#60000
0"
0%
#65000
1!
1$
#67000
b100 &
b1100111001110111100000000000 '
b100 (
b101000000000110000000000011001 1
b11001 2
#70000
0!
0$
#75000
1"
1%
#77000
b1100111001110111100000000000 )
b100 *
b111 +
b111 ,
b111100000000000 -
b0 .
b101000000000110000000000011001 5
b11001 6
#80000
0"
0%
#85000
1!
1$
#87000
b101 &
b101 (
b0 /
b1100111001110111100000000000 1
b111 2
#90000
0!
0$
#95000
1"
1%
#97000
b101 *
b0 0
b1100111001110111100000000000 5
b111 6
#100000
0"
0%
#105000
1!
1$
#107000
b110 &
b1000100010000000000000 '
b110 (
#110000
0!
0$
#115000
1"
1%
#117000
b1000100010000000000000 )
b110 *
b1010 +
b10100 ,
b10000000000000 -
#120000
0"
0%
#125000
1!
1$
#127000
b111 &
b1100111001110111100000000000 '
b111 (
b1000100010000000000000 1
b11110 2
#130000
0!
0$
#135000
1"
1%
#137000
b1100111001110111100000000000 )
b111 *
b111 +
b111 ,
b111100000000000 -
b1000100010000000000000 5
b11110 6
#140000
0"
0%
#145000
1!
1$
#147000
b1000 &
b100000110010100000000000 '
b1000 (
b1100111001110111100000000000 1
b111 2
#150000
0!
0$
#155000
1"
1%
#157000
b100000110010100000000000 )
b1000 *
b11110 +
b11001 ,
b10100000000000 -
b1100111001110111100000000000 5
b111 6
#160000
0"
0%
#165000
1!
1$
#167000
b1001 &
b11111100000000000000000000000000 '
b1001 (
b100000110010100000000000 1
b110111 2
#170000
0!
0$
#175000
1"
1%
b0 +
b0 ,
#177000
b11111100000000000000000000000000 )
b1001 *
b0 -
b101 .
b100000110010100000000000 5
b110111 6
#180000
0"
0%
#185000
1!
1$
#187000
b1010 &
bx '
b1010 (
b101 /
b11111100000000000000000000000000 1
#190000
0!
0$
#195000
1"
1%
#197000
bx )
b1010 *
bx +
bx ,
bx -
b101 0
b11111100000000000000000000000000 5
#200000
0"
0%
#205000
1!
1$
#207000
b1011 &
b1011 (
bx 1
18
#210000
0!
0$
#215000
1"
1%
#220000
0"
0%
#225000
1!
1$
#230000
0!
0$
#235000
1"
1%
#240000
0"
0%
#245000
1!
1$
#250000
0!
0$
#255000
1"
1%
#260000
0"
0%
#265000
1!
1$
#270000
0!
0$
#275000
1"
1%
#280000
0"
b110 #
0%
